ecoindex_journey_scraper
