Metadata-Version: 2.1
Name: ecoindex-journey-scraper
Version: 1.0.1
Summary: Calcul du lecoindex du un parcours
Author: Orange Innovation
Classifier: Development Status :: 3 - Alpha
Classifier: Intended Audience :: Developers
Classifier: Topic :: Software Development :: Build Tools
Classifier: License :: OSI Approved :: MIT License
Classifier: Programming Language :: Python :: 3
Classifier: Operating System :: OS Independent
Requires-Python: >=3.8
